stackit/kms/__init__.py
stackit/kms/api/__init__.py
stackit/kms/api/default_api.py
stackit/kms/api_client.py
stackit/kms/api_response.py
stackit/kms/configuration.py
stackit/kms/exceptions.py
stackit/kms/models/__init__.py
stackit/kms/models/access_scope.py
stackit/kms/models/algorithm.py
stackit/kms/models/create_key_payload.py
stackit/kms/models/create_key_ring_payload.py
stackit/kms/models/create_wrapping_key_payload.py
stackit/kms/models/decrypt_payload.py
stackit/kms/models/decrypted_data.py
stackit/kms/models/encrypt_payload.py
stackit/kms/models/encrypted_data.py
stackit/kms/models/http_error.py
stackit/kms/models/import_key_payload.py
stackit/kms/models/key.py
stackit/kms/models/key_list.py
stackit/kms/models/key_ring.py
stackit/kms/models/key_ring_list.py
stackit/kms/models/protection.py
stackit/kms/models/purpose.py
stackit/kms/models/sign_payload.py
stackit/kms/models/signed_data.py
stackit/kms/models/verified_data.py
stackit/kms/models/verify_payload.py
stackit/kms/models/version.py
stackit/kms/models/version_list.py
stackit/kms/models/wrapping_algorithm.py
stackit/kms/models/wrapping_key.py
stackit/kms/models/wrapping_key_list.py
stackit/kms/models/wrapping_purpose.py
stackit/kms/py.typed
stackit/kms/rest.py
stackit_kms-0.7.0.dist-info/METADATA
stackit_kms-0.7.0.dist-info/WHEEL
stackit_kms-0.7.0.dist-info/licenses/LICENSE.md
stackit_kms-0.7.0.dist-info/licenses/NOTICE.txt
stackit_kms-0.7.0.dist-info/RECORD
